meerkat/__init__.py
meerkat/config.py
meerkat/constants.py
meerkat/dataframe.py
meerkat/datapanel.py
meerkat/display.py
meerkat/env.py
meerkat/errors.py
meerkat/provenance.py
meerkat/row.py
meerkat/state.py
meerkat/version.py
meerkat/block/__init__.py
meerkat/block/abstract.py
meerkat/block/arrow_block.py
meerkat/block/deferred_block.py
meerkat/block/manager.py
meerkat/block/numpy_block.py
meerkat/block/pandas_block.py
meerkat/block/ref.py
meerkat/block/torch_block.py
meerkat/cells/__init__.py
meerkat/cells/abstract.py
meerkat/cells/audio.py
meerkat/cells/spacy.py
meerkat/cells/volume.py
meerkat/cli/__init__.py
meerkat/cli/main.py
meerkat/columns/__init__.py
meerkat/columns/abstract.py
meerkat/columns/deferred/__init__.py
meerkat/columns/deferred/audio.py
meerkat/columns/deferred/base.py
meerkat/columns/deferred/file.py
meerkat/columns/deferred/image.py
meerkat/columns/object/__init__.py
meerkat/columns/object/base.py
meerkat/columns/scalar/__init__.py
meerkat/columns/scalar/abstract.py
meerkat/columns/scalar/arrow.py
meerkat/columns/scalar/pandas.py
meerkat/columns/tensor/__init__.py
meerkat/columns/tensor/abstract.py
meerkat/columns/tensor/numpy.py
meerkat/columns/tensor/torch.py
meerkat/datasets/__init__.py
meerkat/datasets/abstract.py
meerkat/datasets/info.py
meerkat/datasets/registry.py
meerkat/datasets/utils.py
meerkat/datasets/audioset/__init__.py
meerkat/datasets/celeba/__init__.py
meerkat/datasets/coco/__init__.py
meerkat/datasets/dew/__init__.py
meerkat/datasets/eeg/__init__.py
meerkat/datasets/eeg/data_utils.py
meerkat/datasets/enron/__init__.py
meerkat/datasets/expw/__init__.py
meerkat/datasets/fer/__init__.py
meerkat/datasets/gqa/__init__.py
meerkat/datasets/gtsdb/__init__.py
meerkat/datasets/imagenet/__init__.py
meerkat/datasets/imagenette/__init__.py
meerkat/datasets/inaturalist/__init__.py
meerkat/datasets/lra/__init__.py
meerkat/datasets/lra/pathfinder.py
meerkat/datasets/lvis/__init__.py
meerkat/datasets/mimic_iii/__init__.py
meerkat_ml-0.4.11.dist-info/LICENSE.md
meerkat_ml-0.4.11.dist-info/METADATA
meerkat_ml-0.4.11.dist-info/WHEEL
meerkat_ml-0.4.11.dist-info/entry_points.txt
meerkat_ml-0.4.11.dist-info/top_level.txt
meerkat_ml-0.4.11.dist-info/RECORD
