Metadata-Version: 2.1
Name: meerkat-ml
Version: 0.4.11
Summary: Meerkat is building new data abstractions to make machine learning easier.
Home-page: https://github.com/robustness-gym/meerkat
Author: The Meerkat Team
Author-email: kgoel@cs.stanford.edu
License: Apache 2.0
Classifier: Programming Language :: Python
Classifier: Programming Language :: Python :: 3
Classifier: Programming Language :: Python :: 3.6
Classifier: Topic :: Scientific/Engineering :: Artificial Intelligence
Requires-Python: >=3.7.0
License-File: LICENSE.md
Requires-Dist: dataclasses (>=0.6)
Requires-Dist: pandas
Requires-Dist: dill (>=0.3.3)
Requires-Dist: numpy (>=1.18.0)
Requires-Dist: cytoolz
Requires-Dist: ujson
Requires-Dist: torch (>=1.7.0)
Requires-Dist: scikit-learn
Requires-Dist: tqdm (>=4.49.0)
Requires-Dist: datasets (>=1.4.1)
Requires-Dist: pyarrow (>=11.0.0)
Requires-Dist: PyYAML (>=5.4.1)
Requires-Dist: omegaconf (>=2.0.5)
Requires-Dist: semver (>=2.13.0)
Requires-Dist: multiprocess (>=0.70.11)
Requires-Dist: Cython (>=0.29.21)
Requires-Dist: progressbar (>=2.5)
Requires-Dist: fvcore
Requires-Dist: ipywidgets (>=7.0.0)
Requires-Dist: IPython
Requires-Dist: fastapi
Requires-Dist: uvicorn
Requires-Dist: rich
Requires-Dist: cryptography
Requires-Dist: wrapt
Requires-Dist: typer
Requires-Dist: jinja2
Requires-Dist: nbformat
Requires-Dist: sse-starlette
Requires-Dist: tabulate
Requires-Dist: pyparsing
Provides-Extra: all
Requires-Dist: sphinx-autodoc-typehints ; extra == 'all'
Requires-Dist: httpx ; extra == 'all'
Requires-Dist: sphinx-copybutton ; extra == 'all'
Requires-Dist: flake8 (>=3.8.4) ; extra == 'all'
Requires-Dist: pytest-cov (>=2.10.1) ; extra == 'all'
Requires-Dist: kaggle ; extra == 'all'
Requires-Dist: nbsphinx ; extra == 'all'
Requires-Dist: pre-commit (>=2.9.3) ; extra == 'all'
Requires-Dist: pydata-sphinx-theme (==0.8.1) ; extra == 'all'
Requires-Dist: faiss-gpu ; extra == 'all'
Requires-Dist: sphinx (==4.5.0) ; extra == 'all'
Requires-Dist: myst-parser (==0.18.1) ; extra == 'all'
Requires-Dist: sphinx-external-toc ; extra == 'all'
Requires-Dist: torchvision (>=0.9.0) ; extra == 'all'
Requires-Dist: sphinx-design ; extra == 'all'
Requires-Dist: black (==22.12.0) ; extra == 'all'
Requires-Dist: ray ; extra == 'all'
Requires-Dist: toml ; extra == 'all'
Requires-Dist: jupyter-book (==0.6.5) ; extra == 'all'
Requires-Dist: myst-nb (==0.17.1) ; extra == 'all'
Requires-Dist: jinja2 ; extra == 'all'
Requires-Dist: parameterized ; extra == 'all'
Requires-Dist: twine ; extra == 'all'
Requires-Dist: jupyter-sphinx (==0.4.0) ; extra == 'all'
Requires-Dist: sphinx-book-theme ; extra == 'all'
Requires-Dist: pyvoxel ; extra == 'all'
Requires-Dist: google-cloud-storage ; extra == 'all'
Requires-Dist: torchaudio ; extra == 'all'
Requires-Dist: Pillow ; extra == 'all'
Requires-Dist: spacy (>=3.0.0) ; extra == 'all'
Requires-Dist: sphinx-autobuild ; extra == 'all'
Requires-Dist: isort (>=5.12.0) ; extra == 'all'
Requires-Dist: sphinx-panels ; extra == 'all'
Requires-Dist: faiss-cpu ; extra == 'all'
Requires-Dist: setuptools ; extra == 'all'
Requires-Dist: sphinx-remove-toctrees ; extra == 'all'
Requires-Dist: docformatter (>=1.4) ; extra == 'all'
Requires-Dist: umap-learn[plot] ; extra == 'all'
Requires-Dist: recommonmark (>=0.7.1) ; extra == 'all'
Requires-Dist: transformers ; extra == 'all'
Requires-Dist: opencv-python ; extra == 'all'
Requires-Dist: sphinx-toolbox ; extra == 'all'
Requires-Dist: google-cloud-bigquery[bqstorage,pandas] ; extra == 'all'
Requires-Dist: ipython (<8.13.0) ; (python_version <= "3.8") and extra == 'all'
Requires-Dist: ipython ; (python_version >= "3.9") and extra == 'all'
Provides-Extra: audio
Requires-Dist: torchaudio ; extra == 'audio'
Provides-Extra: dev
Requires-Dist: black (==22.12.0) ; extra == 'dev'
Requires-Dist: isort (>=5.12.0) ; extra == 'dev'
Requires-Dist: flake8 (>=3.8.4) ; extra == 'dev'
Requires-Dist: docformatter (>=1.4) ; extra == 'dev'
Requires-Dist: pytest-cov (>=2.10.1) ; extra == 'dev'
Requires-Dist: recommonmark (>=0.7.1) ; extra == 'dev'
Requires-Dist: parameterized ; extra == 'dev'
Requires-Dist: pre-commit (>=2.9.3) ; extra == 'dev'
Requires-Dist: twine ; extra == 'dev'
Requires-Dist: httpx ; extra == 'dev'
Requires-Dist: ray ; extra == 'dev'
Requires-Dist: sphinx-autodoc-typehints ; extra == 'dev'
Requires-Dist: nbsphinx ; extra == 'dev'
Requires-Dist: toml ; extra == 'dev'
Requires-Dist: jupyter-sphinx (==0.4.0) ; extra == 'dev'
Requires-Dist: sphinx-panels ; extra == 'dev'
Requires-Dist: sphinx-autobuild ; extra == 'dev'
Requires-Dist: jupyter-book (==0.6.5) ; extra == 'dev'
Requires-Dist: sphinx-external-toc ; extra == 'dev'
Requires-Dist: sphinx-book-theme ; extra == 'dev'
Requires-Dist: myst-nb (==0.17.1) ; extra == 'dev'
Requires-Dist: myst-parser (==0.18.1) ; extra == 'dev'
Requires-Dist: sphinx-toolbox ; extra == 'dev'
Requires-Dist: sphinx-copybutton ; extra == 'dev'
Requires-Dist: sphinx-design ; extra == 'dev'
Requires-Dist: jinja2 ; extra == 'dev'
Requires-Dist: pydata-sphinx-theme (==0.8.1) ; extra == 'dev'
Requires-Dist: sphinx (==4.5.0) ; extra == 'dev'
Requires-Dist: sphinx-remove-toctrees ; extra == 'dev'
Requires-Dist: setuptools ; extra == 'dev'
Requires-Dist: ipython (<8.13.0) ; (python_version <= "3.8") and extra == 'dev'
Requires-Dist: ipython ; (python_version >= "3.9") and extra == 'dev'
Provides-Extra: embeddings-linux
Requires-Dist: faiss-gpu ; extra == 'embeddings-linux'
Requires-Dist: umap-learn[plot] ; extra == 'embeddings-linux'
Provides-Extra: embeddings-mac
Requires-Dist: faiss-cpu ; extra == 'embeddings-mac'
Requires-Dist: umap-learn[plot] ; extra == 'embeddings-mac'
Provides-Extra: medimg
Requires-Dist: pyvoxel ; extra == 'medimg'
Requires-Dist: kaggle ; extra == 'medimg'
Requires-Dist: google-cloud-storage ; extra == 'medimg'
Requires-Dist: google-cloud-bigquery[bqstorage,pandas] ; extra == 'medimg'
Provides-Extra: text
Requires-Dist: transformers ; extra == 'text'
Requires-Dist: spacy (>=3.0.0) ; extra == 'text'
Provides-Extra: vision
Requires-Dist: torchvision (>=0.9.0) ; extra == 'vision'
Requires-Dist: opencv-python ; extra == 'vision'
Requires-Dist: Pillow ; extra == 'vision'
